<PAMDataset>
  <PAMRasterBand band="1">
    <Metadata>
      <MDI key="STATISTICS_APPROXIMATE">YES</MDI>
      <MDI key="STATISTICS_MINIMUM">0</MDI>
      <MDI key="STATISTICS_MAXIMUM">255</MDI>
      <MDI key="STATISTICS_MEAN">164.93730248683</MDI>
      <MDI key="STATISTICS_STDDEV">38.663093059595</MDI>
      <MDI key="STATISTICS_VALID_PERCENT">92.08</MDI>
    </Metadata>
  </PAMRasterBand>
  <PAMRasterBand band="2">
    <Metadata>
      <MDI key="STATISTICS_APPROXIMATE">YES</MDI>
      <MDI key="STATISTICS_MINIMUM">0</MDI>
      <MDI key="STATISTICS_MAXIMUM">255</MDI>
      <MDI key="STATISTICS_MEAN">166.34708980598</MDI>
      <MDI key="STATISTICS_STDDEV">38.312945185876</MDI>
      <MDI key="STATISTICS_VALID_PERCENT">92.08</MDI>
    </Metadata>
  </PAMRasterBand>
  <PAMRasterBand band="3">
    <Metadata>
      <MDI key="STATISTICS_APPROXIMATE">YES</MDI>
      <MDI key="STATISTICS_MINIMUM">0</MDI>
      <MDI key="STATISTICS_MAXIMUM">255</MDI>
      <MDI key="STATISTICS_MEAN">130.18298553237</MDI>
      <MDI key="STATISTICS_STDDEV">40.987446166398</MDI>
      <MDI key="STATISTICS_VALID_PERCENT">92.08</MDI>
    </Metadata>
  </PAMRasterBand>
</PAMDataset>
