<PAMDataset>
  <PAMRasterBand band="1">
    <Metadata>
      <MDI key="STATISTICS_APPROXIMATE">YES</MDI>
      <MDI key="STATISTICS_MINIMUM">71</MDI>
      <MDI key="STATISTICS_MAXIMUM">244</MDI>
      <MDI key="STATISTICS_MEAN">151.34379285311</MDI>
      <MDI key="STATISTICS_STDDEV">31.629021406753</MDI>
      <MDI key="STATISTICS_VALID_PERCENT">25.46</MDI>
    </Metadata>
  </PAMRasterBand>
  <PAMRasterBand band="2">
    <Metadata>
      <MDI key="STATISTICS_APPROXIMATE">YES</MDI>
      <MDI key="STATISTICS_MINIMUM">72</MDI>
      <MDI key="STATISTICS_MAXIMUM">245</MDI>
      <MDI key="STATISTICS_MEAN">180.42663547633</MDI>
      <MDI key="STATISTICS_STDDEV">24.526528061801</MDI>
      <MDI key="STATISTICS_VALID_PERCENT">25.46</MDI>
    </Metadata>
  </PAMRasterBand>
  <PAMRasterBand band="3">
    <Metadata>
      <MDI key="STATISTICS_APPROXIMATE">YES</MDI>
      <MDI key="STATISTICS_MINIMUM">40</MDI>
      <MDI key="STATISTICS_MAXIMUM">255</MDI>
      <MDI key="STATISTICS_MEAN">174.98959425667</MDI>
      <MDI key="STATISTICS_STDDEV">56.64627515238</MDI>
      <MDI key="STATISTICS_VALID_PERCENT">25.46</MDI>
    </Metadata>
  </PAMRasterBand>
</PAMDataset>
